insegel/__init__.py
insegel/footer.html
insegel/layout.html
insegel/menu.html
insegel/search.html
insegel/searchinput.html
insegel/theme.conf
insegel/static/css/custom.css
insegel/static/css/insegel.css
insegel/static/img/favicon-16x16.png
insegel/static/img/favicon-32x32.png
insegel-1.3.1.dist-info/LICENSE
insegel-1.3.1.dist-info/METADATA
insegel-1.3.1.dist-info/WHEEL
insegel-1.3.1.dist-info/entry_points.txt
insegel-1.3.1.dist-info/top_level.txt
insegel-1.3.1.dist-info/RECORD
