Metadata-Version: 2.1
Name: insegel
Version: 1.3.1
Summary: Clean, minimalist Sphinx theme for deploying on ReadTheDocs
Home-page: https://github.com/autophagy/insegel
Author: Mika Naylor (Autophagy)
Author-email: mail@autophagy.io
License: MIT
Platform: UNKNOWN
Classifier: Framework :: Sphinx
Classifier: Framework :: Sphinx :: Theme
Classifier: Development Status :: 2 - Pre-Alpha
Classifier: License :: OSI Approved :: MIT License
Classifier: Environment :: Console
Classifier: Environment :: Web Environment
Classifier: Intended Audience :: Developers
Classifier: Programming Language :: Python :: 3
Classifier: Operating System :: OS Independent
Classifier: Topic :: Documentation
Classifier: Topic :: Software Development :: Documentation
